universal/__init__.py
universal/algo.py
universal/asset_filters.py
universal/result.py
universal/tools.py
universal/algos/__init__.py
universal/algos/_up_deprecated.py
universal/algos/anticor.py
universal/algos/bah.py
universal/algos/bcrp.py
universal/algos/best_markowitz.py
universal/algos/best_so_far.py
universal/algos/bnn.py
universal/algos/corn.py
universal/algos/crp.py
universal/algos/cwmr.py
universal/algos/dynamic_crp.py
universal/algos/eg.py
universal/algos/estimators.py
universal/algos/kelly.py
universal/algos/mpt.py
universal/algos/olmar.py
universal/algos/ons.py
universal/algos/pamr.py
universal/algos/rmr.py
universal/algos/rprt.py
universal/algos/single_index_covariance_estimator.py
universal/algos/tco.py
universal/algos/up.py
universal/algos/wmamr.py
universal/algos/ternary/__init__.py
universal/algos/ternary/plotting.py
universal/data/djia.csv
universal/data/msci.csv
universal/data/nyse_n.csv
universal/data/nyse_o.csv
universal/data/sp500.csv
universal/data/tse.csv
universal/data/jpm_assumptions/jpm-matrix-eur-2021.xlsx
universal/data/jpm_assumptions/jpm-matrix-usd-2018.xlsx
universal/data/jpm_assumptions/jpm-matrix-usd-2019.xlsx
universal/data/jpm_assumptions/jpm-matrix-usd-2020.xlsx
universal/data/jpm_assumptions/jpm-matrix-usd-2021.xlsx
universal_portfolios-0.4.15.dist-info/METADATA
universal_portfolios-0.4.15.dist-info/WHEEL
universal_portfolios-0.4.15.dist-info/licenses/LICENSE
universal_portfolios-0.4.15.dist-info/RECORD
