Metadata-Version: 2.4
Name: universal-portfolios
Version: 0.4.15
Summary: Collection of algorithms for online portfolio selection
Project-URL: Repository, https://github.com/Marigold/universal-portfolios
Author-email: Marigold <mojmir.vinkler@gmail.com>
License-File: LICENSE
Requires-Python: <3.13,>=3.10
Requires-Dist: cvxopt>=1.3.0
Requires-Dist: matplotlib>=3.3.1
Requires-Dist: numpy>=2.0.0
Requires-Dist: pandas-datareader>=0.10.0
Requires-Dist: pandas>=1.1.1
Requires-Dist: pillow>=9.2.0
Requires-Dist: plotly>=5.21.0
Requires-Dist: requests>=2.24.0
Requires-Dist: scikit-learn>=1.1.1
Requires-Dist: scipy>=1.8.1
Requires-Dist: seaborn>=0.13.2
Requires-Dist: statsmodels>=0.13.2
Requires-Dist: tqdm>=4.56.2
Requires-Dist: urllib3>=1.26.6
Requires-Dist: yfinance>=0.2.31
